aamp/__init__.py
aamp/__main__.py
aamp/_version.py
aamp/aamp.py
aamp/botw_hashed_names.py
aamp/botw_hashed_names.txt
aamp/botw_numbered_names.py
aamp/botw_numbered_names.txt
aamp/converters.py
aamp/parameters.py
aamp/util.py
aamp/yaml_util.py
aamp-1.4.1.post1.dist-info/LICENSE
aamp-1.4.1.post1.dist-info/METADATA
aamp-1.4.1.post1.dist-info/WHEEL
aamp-1.4.1.post1.dist-info/entry_points.txt
aamp-1.4.1.post1.dist-info/top_level.txt
aamp-1.4.1.post1.dist-info/RECORD
