Metadata-Version: 2.1
Name: aamp
Version: 1.4.1.post1
Summary: Nintendo parameter archive (AAMP) library
Home-page: https://github.com/leoetlino/aamp
Author: leoetlino
Author-email: leo@leolam.fr
Classifier: License :: OSI Approved :: GNU General Public License v2 or later (GPLv2+)
Classifier: Operating System :: OS Independent
Classifier: Programming Language :: Python :: 3 :: Only
Classifier: Topic :: Software Development :: Libraries
Requires-Python: >=3.6
License-File: LICENSE
Requires-Dist: PyYAML ~=6.0
Requires-Dist: dataclasses ; python_version == "3.6"
